gviewer/__init__.py
gviewer/action.py
gviewer/basic_widget.py
gviewer/config.py
gviewer/context.py
gviewer/controller.py
gviewer/displayer.py
gviewer/parent.py
gviewer/store.py
gviewer/util.py
gviewer/version.py
gviewer/viewer.py
gviewer/keys/__init__.py
gviewer/keys/vim.py
gviewer/styles/__init__.py
gviewer/styles/default.py
gviewer/styles/util.py
gviewer/tests/__init__.py
gviewer/tests/test_action.py
gviewer/tests/test_basic_widget.py
gviewer/tests/test_config.py
gviewer/tests/test_controller.py
gviewer/tests/test_parent.py
gviewer/tests/test_store.py
gviewer/tests/test_util.py
gviewer/tests/util.py
gviewer/tests/styles/__init__.py
gviewer/tests/styles/test_util.py
gviewer/tests/view/__init__.py
gviewer/tests/view/test_detail.py
gviewer/tests/view/test_element.py
gviewer/tests/view/test_error.py
gviewer/tests/view/test_helper.py
gviewer/tests/view/test_summary.py
gviewer/view/__init__.py
gviewer/view/detail.py
gviewer/view/element.py
gviewer/view/error.py
gviewer/view/helper.py
gviewer/view/summary.py
gviewer-3.0.6.dist-info/DESCRIPTION.rst
gviewer-3.0.6.dist-info/METADATA
gviewer-3.0.6.dist-info/RECORD
gviewer-3.0.6.dist-info/WHEEL
gviewer-3.0.6.dist-info/metadata.json
gviewer-3.0.6.dist-info/top_level.txt
