Metadata-Version: 2.0
Name: gviewer
Version: 3.0.6
Summary: General Viewer
Home-page: https://github.com/chhsiao90/gviewer
Author: chhsiao90
Author-email: chhsiao90@gmail.com
License: MIT
Platform: UNKNOWN
Classifier: License :: OSI Approved :: MIT License
Classifier: Environment :: Console
Classifier: Environment :: Console :: Curses
Classifier: Operating System :: MacOS :: MacOS X
Classifier: Operating System :: POSIX
Classifier: Programming Language :: Python
Classifier: Programming Language :: Python :: 2
Classifier: Programming Language :: Python :: 2.7
Classifier: Programming Language :: Python :: Implementation :: CPython
Classifier: Programming Language :: Python :: Implementation :: PyPy
Classifier: Topic :: Software Development :: Libraries :: Python Modules
Classifier: Topic :: Software Development :: Widget Sets
Requires-Dist: urwid (==1.3.1)
Provides-Extra: dev
Requires-Dist: Pygments (==2.1.3); extra == 'dev'
Requires-Dist: mock (==2.0.0); extra == 'dev'
